public static void main(java.lang.String[]);
  Code:
     0: new           #2                  // class java/lang/Thread
     3: dup
     4: new           #3                  // class com/example/myapplication/lambda/LambdaTest$1
     7: dup
     8: invokespecial #4                  // Method com/example/myapplication/lambda/LambdaTest$1."<init>":()V
    11: invokespecial #5                  // Method java/lang/Thread."<init>":(Ljava/lang/Runnable;)V
    14: invokevirtual #6                  // Method java/lang/Thread.start:()V
    17: return
    
    public static void main(java.lang.String[]);
  Code:
     0: new           #2                  // class java/lang/Thread
     3: dup
     4: invokedynamic #3,  0              // InvokeDynamic #0:run:()Ljava/lang/Runnable;
     9: invokespecial #4                  // Method java/lang/Thread."<init>":(Ljava/lang/Runnable;)V
    12: invokevirtual #5                  // Method java/lang/Thread.start:()V
    15: return